README.md
setup.py
bin/syndle
syndle/__init__.py
syndle/gradle.py
syndle/remote.py
syndle/service.py
syndle.egg-info/PKG-INFO
syndle.egg-info/SOURCES.txt
syndle.egg-info/dependency_links.txt
syndle.egg-info/not-zip-safe
syndle.egg-info/requires.txt
syndle.egg-info/top_level.txt