Metadata-Version: 1.0
Name: syndle
Version: 0.1
Summary: sync gradle dependency to local maven
Home-page: http://github.com/Jintin/syndle
Author: jintin
Author-email: jintinapps@gmail.com
License: MIT
Keywords: android gradle config build version dependency sync
Platform: UNKNOWN
